remoteService/__init__.py
remoteService/add.py
remoteService/subtract.py
remoteService-0.0.1.dist-info/METADATA
remoteService-0.0.1.dist-info/WHEEL
remoteService-0.0.1.dist-info/top_level.txt
remoteService-0.0.1.dist-info/RECORD
